hello_assomgitdev-0.1.0.dist-info/METADATA
hello_assomgitdev-0.1.0.dist-info/WHEEL
hello_assomgitdev/__init__.py
hello_assomgitdev-0.1.0.dist-info/RECORD
