Metadata-Version: 2.1
Name: hello-assomgitdev
Version: 0.1.0
Summary: first my python
Author-Email: juseon <assomggm@gmail.com>
License: MIT
Requires-Python: >=3.8
